{
    "description": "Given an array <code>nums</code> of integers, return <em>the length of the longest arithmetic subsequence in</em> <code>nums</code>.\n\n<strong>Note</strong> that:\n\n",
    "tags": [
        {
            "name": "Array",
            "url": "https://leetcode.com/tag/array/"
        },
        {
            "name": "Hash Table",
            "url": "https://leetcode.com/tag/hash-table/"
        },
        {
            "name": "Binary Search",
            "url": "https://leetcode.com/tag/binary-search/"
        },
        {
            "name": "Dynamic Programming",
            "url": "https://leetcode.com/tag/dynamic-programming/"
        }
    ]
}