{
    "description": "You are given four integers <code>row</code>, <code>cols</code>, <code>rCenter</code>, and <code>cCenter</code>. There is a <code>rows x cols</code> matrix and you are on the cell with the coordinates <code>(rCenter, cCenter)</code>.\n\nReturn <em>the coordinates of all cells in the matrix, sorted by their <strong>distance</strong> from </em><code>(rCenter, cCenter)</code><em> from the smallest distance to the largest distance</em>. You may return the answer in <strong>any order</strong> that satisfies this condition.\n\nThe <strong>distance</strong> between two cells <code>(r<sub>1</sub>, c<sub>1</sub>)</code> and <code>(r<sub>2</sub>, c<sub>2</sub>)</code> is <code>|r<sub>1</sub> - r<sub>2</sub>| + |c<sub>1</sub> - c<sub>2</sub>|</code>.\n\n",
    "tags": [
        {
            "name": "Array",
            "url": "https://leetcode.com/tag/array/"
        },
        {
            "name": "Math",
            "url": "https://leetcode.com/tag/math/"
        },
        {
            "name": "Geometry",
            "url": "https://leetcode.com/tag/geometry/"
        },
        {
            "name": "Sorting",
            "url": "https://leetcode.com/tag/sorting/"
        },
        {
            "name": "Matrix",
            "url": "https://leetcode.com/tag/matrix/"
        }
    ]
}