{
    "description": "Given an <code>m x n</code> binary matrix <code>mat</code>, return <em>the number of special positions in </em><code>mat</code><em>.</em>\n\nA position <code>(i, j)</code> is called <strong>special</strong> if <code>mat[i][j] == 1</code> and all other elements in row <code>i</code> and column <code>j</code> are <code>0</code> (rows and columns are <strong>0-indexed</strong>).\n\n",
    "tags": [
        {
            "name": "Array",
            "url": "https://leetcode.com/tag/array/"
        },
        {
            "name": "Matrix",
            "url": "https://leetcode.com/tag/matrix/"
        }
    ]
}