{
    "description": "Given a string <code>s</code>, return <em>the number of <strong>homogenous</strong> substrings of </em><code>s</code><em>.</em> Since the answer may be too large, return it <strong>modulo</strong> <code>10<sup>9</sup> + 7</code>.\n\nA string is <strong>homogenous</strong> if all the characters of the string are the same.\n\nA <strong>substring</strong> is a contiguous sequence of characters within a string.\n\n",
    "tags": [
        {
            "name": "Math",
            "url": "https://leetcode.com/tag/math/"
        },
        {
            "name": "String",
            "url": "https://leetcode.com/tag/string/"
        }
    ]
}