{
    "description": "You are given an integer array <code>matches</code> where <code>matches[i] = [winner<sub>i</sub>, loser<sub>i</sub>]</code> indicates that the player <code>winner<sub>i</sub></code> defeated player <code>loser<sub>i</sub></code> in a match.\n\nReturn <em>a list </em><code>answer</code><em> of size </em><code>2</code><em> where:</em>\n\nThe values in the two lists should be returned in <strong>increasing</strong> order.\n\n<strong>Note:</strong>\n\n",
    "tags": [
        {
            "name": "Array",
            "url": "https://leetcode.com/tag/array/"
        },
        {
            "name": "Hash Table",
            "url": "https://leetcode.com/tag/hash-table/"
        },
        {
            "name": "Sorting",
            "url": "https://leetcode.com/tag/sorting/"
        },
        {
            "name": "Counting",
            "url": "https://leetcode.com/tag/counting/"
        }
    ]
}