{
    "description": "You are given a <strong>0-indexed</strong> string <code>s</code> consisting of only lowercase English letters, where each letter in <code>s</code> appears <strong>exactly</strong> <strong>twice</strong>. You are also given a <strong>0-indexed</strong> integer array <code>distance</code> of length <code>26</code>.\n\nEach letter in the alphabet is numbered from <code>0</code> to <code>25</code> (i.e. <code>'a' -&gt; 0</code>, <code>'b' -&gt; 1</code>, <code>'c' -&gt; 2</code>, ... , <code>'z' -&gt; 25</code>).\n\nIn a <strong>well-spaced</strong> string, the number of letters between the two occurrences of the <code>i<sup>th</sup></code> letter is <code>distance[i]</code>. If the <code>i<sup>th</sup></code> letter does not appear in <code>s</code>, then <code>distance[i]</code> can be <strong>ignored</strong>.\n\nReturn <code>true</code><em> if </em><code>s</code><em> is a <strong>well-spaced</strong> string, otherwise return </em><code>false</code>.\n\n",
    "tags": [
        {
            "name": "Array",
            "url": "https://leetcode.com/tag/array/"
        },
        {
            "name": "Hash Table",
            "url": "https://leetcode.com/tag/hash-table/"
        },
        {
            "name": "String",
            "url": "https://leetcode.com/tag/string/"
        }
    ]
}