{
    "description": "You are given a string <code>target</code>, an array of strings <code>words</code>, and an integer array <code>costs</code>, both arrays of the same length.\n\nImagine an empty string <code>s</code>.\n\nYou can perform the following operation any number of times (including <strong>zero</strong>):\n\nReturn the <strong>minimum</strong> cost to make <code>s</code> equal to <code>target</code>. If it's not possible, return <code>-1</code>.\n\n",
    "tags": [
        {
            "name": "Array",
            "url": "https://leetcode.com/tag/array/"
        },
        {
            "name": "String",
            "url": "https://leetcode.com/tag/string/"
        },
        {
            "name": "Dynamic Programming",
            "url": "https://leetcode.com/tag/dynamic-programming/"
        },
        {
            "name": "Suffix Array",
            "url": "https://leetcode.com/tag/suffix-array/"
        }
    ]
}