{
    "description": "Given two strings <code>word1</code> and <code>word2</code>, return <em>the minimum number of operations required to convert <code>word1</code> to <code>word2</code></em>.\n\nYou have the following three operations permitted on a word:\n\n",
    "tags": [
        {
            "name": "String",
            "url": "https://leetcode.com/tag/string/"
        },
        {
            "name": "Dynamic Programming",
            "url": "https://leetcode.com/tag/dynamic-programming/"
        }
    ]
}