{
    "description": "Design a data structure that efficiently finds the <strong>majority element</strong> of a given subarray.\n\nThe <strong>majority element</strong> of a subarray is an element that occurs <code>threshold</code> times or more in the subarray.\n\nImplementing the <code>MajorityChecker</code> class:\n\n",
    "tags": [
        {
            "name": "Array",
            "url": "https://leetcode.com/tag/array/"
        },
        {
            "name": "Binary Search",
            "url": "https://leetcode.com/tag/binary-search/"
        },
        {
            "name": "Design",
            "url": "https://leetcode.com/tag/design/"
        },
        {
            "name": "Binary Indexed Tree",
            "url": "https://leetcode.com/tag/binary-indexed-tree/"
        },
        {
            "name": "Segment Tree",
            "url": "https://leetcode.com/tag/segment-tree/"
        }
    ]
}