{
    "description": "You are given the string <code>croakOfFrogs</code>, which represents a combination of the string <code>\"croak\"</code> from different frogs, that is, multiple frogs can croak at the same time, so multiple <code>\"croak\"</code> are mixed.\n\n<em>Return the minimum number of </em>different<em> frogs to finish all the croaks in the given string.</em>\n\nA valid <code>\"croak\"</code> means a frog is printing five letters <code>'c'</code>, <code>'r'</code>, <code>'o'</code>, <code>'a'</code>, and <code>'k'</code> <strong>sequentially</strong>. The frogs have to print all five letters to finish a croak. If the given string is not a combination of a valid <code>\"croak\"</code> return <code>-1</code>.\n\n",
    "tags": [
        {
            "name": "String",
            "url": "https://leetcode.com/tag/string/"
        },
        {
            "name": "Counting",
            "url": "https://leetcode.com/tag/counting/"
        }
    ]
}