{
    "description": "You are given an integer array <code>nums</code> and two integers <code>limit</code> and <code>goal</code>. The array <code>nums</code> has an interesting property that <code>abs(nums[i]) &lt;= limit</code>.\n\nReturn <em>the minimum number of elements you need to add to make the sum of the array equal to </em><code>goal</code>. The array must maintain its property that <code>abs(nums[i]) &lt;= limit</code>.\n\nNote that <code>abs(x)</code> equals <code>x</code> if <code>x &gt;= 0</code>, and <code>-x</code> otherwise.\n\n",
    "tags": [
        {
            "name": "Array",
            "url": "https://leetcode.com/tag/array/"
        },
        {
            "name": "Greedy",
            "url": "https://leetcode.com/tag/greedy/"
        }
    ]
}