{
    "description": "You are given two integers, <code>m</code> and <code>k</code>, and a stream of integers. You are tasked to implement a data structure that calculates the <strong>MKAverage</strong> for the stream.\n\nThe <strong>MKAverage</strong> can be calculated using these steps:\n\nImplement the <code>MKAverage</code> class:\n\n",
    "tags": [
        {
            "name": "Design",
            "url": "https://leetcode.com/tag/design/"
        },
        {
            "name": "Queue",
            "url": "https://leetcode.com/tag/queue/"
        },
        {
            "name": "Heap (Priority Queue)",
            "url": "https://leetcode.com/tag/heap-priority-queue/"
        },
        {
            "name": "Data Stream",
            "url": "https://leetcode.com/tag/data-stream/"
        },
        {
            "name": "Ordered Set",
            "url": "https://leetcode.com/tag/ordered-set/"
        }
    ]
}