{
    "description": "Given an array of integers <code>nums</code>&nbsp;and an integer <code>target</code>, return <em>indices of the two numbers such that they add up to <code>target</code></em>.\n\nYou may assume that each input would have <strong><em>exactly</em> one solution</strong>, and you may not use the <em>same</em> element twice.\n\nYou can return the answer in any order.\n\n",
    "tags": [
        {
            "name": "Array",
            "url": "https://leetcode.com/tag/array/"
        },
        {
            "name": "Hash Table",
            "url": "https://leetcode.com/tag/hash-table/"
        }
    ]
}