{
    "description": "You are given a stream of <strong>records</strong> about a particular stock. Each record contains a <strong>timestamp</strong> and the corresponding <strong>price</strong> of the stock at that timestamp.\n\nUnfortunately due to the volatile nature of the stock market, the records do not come in order. Even worse, some records may be incorrect. Another record with the same timestamp may appear later in the stream <strong>correcting</strong> the price of the previous wrong record.\n\nDesign an algorithm that:\n\nImplement the <code>StockPrice</code> class:\n\n",
    "tags": [
        {
            "name": "Hash Table",
            "url": "https://leetcode.com/tag/hash-table/"
        },
        {
            "name": "Design",
            "url": "https://leetcode.com/tag/design/"
        },
        {
            "name": "Heap (Priority Queue)",
            "url": "https://leetcode.com/tag/heap-priority-queue/"
        },
        {
            "name": "Data Stream",
            "url": "https://leetcode.com/tag/data-stream/"
        },
        {
            "name": "Ordered Set",
            "url": "https://leetcode.com/tag/ordered-set/"
        }
    ]
}