{
    "description": "You are given an array of <code>k</code> linked-lists <code>lists</code>, each linked-list is sorted in ascending order.\n\n<em>Merge all the linked-lists into one sorted linked-list and return it.</em>\n\n",
    "tags": [
        {
            "name": "Linked List",
            "url": "https://leetcode.com/tag/linked-list/"
        },
        {
            "name": "Divide and Conquer",
            "url": "https://leetcode.com/tag/divide-and-conquer/"
        },
        {
            "name": "Heap (Priority Queue)",
            "url": "https://leetcode.com/tag/heap-priority-queue/"
        },
        {
            "name": "Merge Sort",
            "url": "https://leetcode.com/tag/merge-sort/"
        }
    ]
}