{
    "description": "You are given a <strong>0-indexed</strong> integer array <code>costs</code> where <code>costs[i]</code> is the cost of hiring the <code>i<sup>th</sup></code> worker.\n\nYou are also given two integers <code>k</code> and <code>candidates</code>. We want to hire exactly <code>k</code> workers according to the following rules:\n\nReturn <em>the total cost to hire exactly </em><code>k</code><em> workers.</em>\n\n",
    "tags": [
        {
            "name": "Array",
            "url": "https://leetcode.com/tag/array/"
        },
        {
            "name": "Two Pointers",
            "url": "https://leetcode.com/tag/two-pointers/"
        },
        {
            "name": "Heap (Priority Queue)",
            "url": "https://leetcode.com/tag/heap-priority-queue/"
        },
        {
            "name": "Simulation",
            "url": "https://leetcode.com/tag/simulation/"
        }
    ]
}