{
    "description": "You are given an array of positive integers <code>price</code> where <code>price[i]</code> denotes the price of the <code>i<sup>th</sup></code> candy and a positive integer <code>k</code>.\n\nThe store sells baskets of <code>k</code> <strong>distinct</strong> candies. The <strong>tastiness</strong> of a candy basket is the smallest absolute difference of the <strong>prices</strong> of any two candies in the basket.\n\nReturn <em>the <strong>maximum</strong> tastiness of a candy basket.</em>\n\n",
    "tags": [
        {
            "name": "Array",
            "url": "https://leetcode.com/tag/array/"
        },
        {
            "name": "Binary Search",
            "url": "https://leetcode.com/tag/binary-search/"
        },
        {
            "name": "Greedy",
            "url": "https://leetcode.com/tag/greedy/"
        },
        {
            "name": "Sorting",
            "url": "https://leetcode.com/tag/sorting/"
        }
    ]
}