{
    "description": "You are given a <strong>binary</strong> string <code>s</code> and an integer <code>k</code>.\n\nYou are also given a 2D integer array <code>queries</code>, where <code>queries[i] = [l<sub>i</sub>, r<sub>i</sub>]</code>.\n\nA <strong>binary string</strong> satisfies the <strong>k-constraint</strong> if <strong>either</strong> of the following conditions holds:\n\nReturn an integer array <code>answer</code>, where <code>answer[i]</code> is the number of <span data-keyword=\"substring-nonempty\" class=\" cursor-pointer relative text-dark-blue-s text-sm\"><div class=\"popover-wrapper inline-block\" data-headlessui-state=\"\"><div><div aria-expanded=\"false\" data-headlessui-state=\"\" id=\"headlessui-popover-button-:ro:\"><div>substrings</div></div><div style=\"position: fixed; z-index: 40; inset: 0px auto auto 0px; transform: translate(58px, 459px);\"></div></div></div></span> of <code>s[l<sub>i</sub>..r<sub>i</sub>]</code> that satisfy the <strong>k-constraint</strong>.\n\n",
    "tags": [
        {
            "name": "Array",
            "url": "https://leetcode.com/tag/array/"
        },
        {
            "name": "String",
            "url": "https://leetcode.com/tag/string/"
        },
        {
            "name": "Binary Search",
            "url": "https://leetcode.com/tag/binary-search/"
        },
        {
            "name": "Sliding Window",
            "url": "https://leetcode.com/tag/sliding-window/"
        },
        {
            "name": "Prefix Sum",
            "url": "https://leetcode.com/tag/prefix-sum/"
        }
    ]
}