{
    "description": "A <strong>complete binary tree</strong> is a binary tree in which every level, except possibly the last, is completely filled, and all nodes are as far left as possible.\n\nDesign an algorithm to insert a new node to a complete binary tree keeping it complete after the insertion.\n\nImplement the <code>CBTInserter</code> class:\n\n",
    "tags": [
        {
            "name": "Tree",
            "url": "https://leetcode.com/tag/tree/"
        },
        {
            "name": "Breadth-First Search",
            "url": "https://leetcode.com/tag/breadth-first-search/"
        },
        {
            "name": "Design",
            "url": "https://leetcode.com/tag/design/"
        },
        {
            "name": "Binary Tree",
            "url": "https://leetcode.com/tag/binary-tree/"
        }
    ]
}